{"variables":[],"nodesData":[{"position":{"x":357.3250435332153,"y":313.0659062918329},"nodeDescription":{"nodeTitle":"Begin","execIn":false,"pinExecInId":null,"execOut":{"execOut0":{"execOutTitle":null,"pinExecOutId":"867","outOrder":0}},"color":"Begin","rows":2,"colums":10}},{"position":{"x":428.21550621369454,"y":459.32412403261173},"nodeDescription":{"nodeTitle":"Print","execIn":true,"pinExecInId":"810","execOut":{"execOut0":{"execOutTitle":null,"pinExecOutId":"811","outOrder":0}},"inputs":{"input0":{"inputTitle":"Value","dataType":"Data","defValue":"(()=>33)()","pinInId":"812"}},"color":"Print","rows":3,"colums":12}}],"wireData":[{"srcId":"867","destId":"810"}]}